Metadata-Version: 2.1
Name: my-secrets-safe-library-bt
Version: 1.0
Summary: Password Safe API integration written in Python, Abstract complexity of managing secrets with the API.
Author: BeyondTrust Corporation
Author-email: support@beyondtrust.com
License: MIT
Project-URL: support, https://www.beyondtrust.com/docs/index.htm#support
Keywords: beyondtrust,devops,secrets,secretssafe,security
Classifier: Programming Language :: Python :: 3
Classifier: License :: OSI Approved :: MIT License
Requires-Python: >=3.11
License-File: LICENSE
